{
    "name": "Emakefun Gesture Recognizer",
    "version": "1.0.0",
    "description": "",
    "license": "MIT",
    "dependencies": {
        "core": "*",
        "radio": "*",
        "microphone": "*"
    },
    "files": [
        "README.md",
        "main.blocks",
        "main.ts",
        "_locales/zh/Emakefun Gesture Recognizer-strings.json",
        "_locales/zh/Emakefun Gesture Recognizer-jsdoc-strings.json"
    ],
    "testFiles": [
        "test.ts"
    ],
    "public": true,
    "supportedTargets": [
        "microbit"
    ],
    "preferredEditor": "blocksprj"
}